{
    "results": [
        {
            "week_number": 2,
            "day_of_week": 2,
            "group_name": "ТЭМ-51",
            "lesson_number": 1,
            "subgroup": 2,
            "subject": "УП.03",
            "instructor": "Фёдоров К.А.",
            "classroom": "РЦ-3"
        },
        {
            "week_number": 2,
            "day_of_week": 2,
            "group_name": "ТЭМ-51",
            "lesson_number": 2,
            "subgroup": 2,
            "subject": "УП.03",
            "instructor": "Фёдоров К.А.",
            "classroom": "РЦ-3"
        },
        {
            "week_number": 2,
            "day_of_week": 2,
            "group_name": "ТЭМ-51",
            "lesson_number": 3,
            "subgroup": 1,
            "subject": "УП.03",
            "instructor": "Фёдоров К.А.",
            "classroom": "РЦ-3"
        },
        {
            "week_number": 2,
            "day_of_week": 2,
            "group_name": "ТЭМ-51",
            "lesson_number": 4,
            "subgroup": 1,
            "subject": "УП.03",
            "instructor": "Фёдоров К.А.",
            "classroom": "РЦ-3"
        },
        {
            "week_number": 2,
            "day_of_week": 2,
            "group_name": "ТЭМ-53",
            "lesson_number": 1,
            "subgroup": 0,
            "subject": "Техн.оборуд.и присп.",
            "instructor": "Удрас Д.Н.",
            "classroom": "РЦ-2"
        },
        {
            "week_number": 2,
            "day_of_week": 2,
            "group_name": "ТЭМ-54",
            "lesson_number": 2,
            "subgroup": 0,
            "subject": "Физика",
            "instructor": "Репин П.В.",
            "classroom": "538"
        },
        {
            "week_number": 2,
            "day_of_week": 2,
            "group_name": "Л-11",
            "lesson_number": 3,
            "subgroup": 2,
            "subject": "Осн.кач.кол.анализа природ.и промышл.",
            "instructor": "Назарова Л.А.",
            "classroom": "121"
        },
        {
            "week_number": 2,
            "day_of_week": 2,
            "group_name": "Л-11",
            "lesson_number": 6,
            "subgroup": 1,
            "subject": "Осн.кач.кол.анализа природ.и промышл.",
            "instructor": "Назарова Л.А.",
            "classroom": "121"
        },
        {
            "week_number": 2,
            "day_of_week": 2,
            "group_name": "БД-142",
            "lesson_number": 2,
            "subgroup": 0,
            "subject": "ВР по проф.Агент банка",
            "instructor": "Маслова Д.Б.",
            "classroom": "304"
        },
        {
            "week_number": 2,
            "day_of_week": 2,
            "group_name": "БД-142",
            "lesson_number": 3,
            "subgroup": 0,
            "subject": "ВР по проф.Агент банка",
            "instructor": "Маслова Д.Б.",
            "classroom": "304"
        },
        {
            "week_number": 2,
            "day_of_week": 2,
            "group_name": "БД-142",
            "lesson_number": 4,
            "subgroup": 0,
            "subject": "ВР по проф.Агент банка",
            "instructor": "Маслова Д.Б.",
            "classroom": "304"
        },
        {
            "week_number": 2,
            "day_of_week": 2,
            "group_name": "БД-142",
            "lesson_number": 5,
            "subgroup": 0,
            "subject": "Физ-ра",
            "instructor": "Фризен Л.Н.",
            "classroom": "С/з 3"
        },
        {
            "week_number": 2,
            "day_of_week": 2,
            "group_name": "БД-143",
            "lesson_number": 4,
            "subgroup": 0,
            "subject": "Экол.осн.природопольз.",
            "instructor": "Моногарова И.В.",
            "classroom": "515"
        },
        {
            "week_number": 2,
            "day_of_week": 2,
            "group_name": "БД-143",
            "lesson_number": 6,
            "subgroup": 0,
            "subject": "Эл-ты высшей математики",
            "instructor": "Бакаева С.Х.",
            "classroom": "226"
        },
        {
            "week_number": 2,
            "day_of_week": 2,
            "group_name": "ДОУ1-92",
            "lesson_number": 1,
            "subgroup": 0,
            "subject": "Управ-ние персоналом",
            "instructor": "Уленкова Е.В.",
            "classroom": "211"
        },
        {
            "week_number": 2,
            "day_of_week": 2,
            "group_name": "ДОУ1-92",
            "lesson_number": 2,
            "subgroup": 0,
            "subject": "Управ-ние персоналом",
            "instructor": "Уленкова Е.В.",
            "classroom": "211"
        },
        {
            "week_number": 2,
            "day_of_week": 2,
            "group_name": "ДОУ1-93",
            "lesson_number": 1,
            "subgroup": 0,
            "subject": "Рус.яз. в ПД",
            "instructor": "Михайленко Т.С.",
            "classroom": "212"
        },
        {
            "week_number": 2,
            "day_of_week": 2,
            "group_name": "ДОУ1-93",
            "lesson_number": 2,
            "subgroup": 0,
            "subject": "Рус.яз. в ПД",
            "instructor": "Михайленко Т.С.",
            "classroom": "212"
        },
        {
            "week_number": 2,
            "day_of_week": 2,
            "group_name": "ДОУ2-92",
            "lesson_number": 1,
            "subgroup": 1,
            "subject": "Гос.и муниципальн.архивы",
            "instructor": "Нуриева А.С.",
            "classroom": "РЦ-7"
        },
        {
            "week_number": 2,
            "day_of_week": 2,
            "group_name": "ДОУ2-92",
            "lesson_number": 2,
            "subgroup": 1,
            "subject": "Гос.и муниципальн.архивы",
            "instructor": "Нуриева А.С.",
            "classroom": "РЦ-7"
        },
        {
            "week_number": 2,
            "day_of_week": 2,
            "group_name": "ДОУ2-92",
            "lesson_number": 3,
            "subgroup": 2,
            "subject": "Гос.и муниципальн.архивы",
            "instructor": "Нуриева А.С.",
            "classroom": "РЦ-7"
        },
        {
            "week_number": 2,
            "day_of_week": 2,
            "group_name": "ДОУ2-92",
            "lesson_number": 4,
            "subgroup": 2,
            "subject": "Гос.и муниципальн.архивы",
            "instructor": "Нуриева А.С.",
            "classroom": "РЦ-7"
        },
        {
            "week_number": 2,
            "day_of_week": 2,
            "group_name": "ДОУ2-93",
            "lesson_number": 5,
            "subgroup": 1,
            "subject": "Орг. и НПО архив.дела",
            "instructor": "Нуриева А.С.",
            "classroom": "543"
        },
        {
            "week_number": 2,
            "day_of_week": 2,
            "group_name": "ДОУ2-93",
            "lesson_number": 6,
            "subgroup": 1,
            "subject": "Орг. и НПО архив.дела",
            "instructor": "Нуриева А.С.",
            "classroom": "543"
        },
        {
            "week_number": 2,
            "day_of_week": 2,
            "group_name": "ДОУ-94",
            "lesson_number": 1,
            "subgroup": 0,
            "subject": "Осн.безоп.защ.Родины",
            "instructor": "Рогова А.Ф.",
            "classroom": "124"
        },
        {
            "week_number": 2,
            "day_of_week": 2,
            "group_name": "ДОУ-94",
            "lesson_number": 2,
            "subgroup": 0,
            "subject": "Рус.язык",
            "instructor": "Царегородцева Е.В.",
            "classroom": "206"
        },
        {
            "week_number": 2,
            "day_of_week": 2,
            "group_name": "БП1-112",
            "lesson_number": 2,
            "subgroup": 0,
            "subject": "Менеджмент в ПД",
            "instructor": "Угарова А.С.",
            "classroom": "124"
        },
        {
            "week_number": 2,
            "day_of_week": 2,
            "group_name": "БП1-112",
            "lesson_number": 5,
            "subgroup": 2,
            "subject": "Ин.яз.в ПД",
            "instructor": "Угарова А.С.",
            "classroom": "301"
        },
        {
            "week_number": 2,
            "day_of_week": 2,
            "group_name": "БП1-113",
            "lesson_number": 2,
            "subgroup": 0,
            "subject": "Эл-ты высшей математики",
            "instructor": "Рушковская Т.Ю.",
            "classroom": "532"
        },
        {
            "week_number": 2,
            "day_of_week": 2,
            "group_name": "БП1-114",
            "lesson_number": 1,
            "subgroup": 0,
            "subject": "География",
            "instructor": "Рунг К.М.",
            "classroom": "1 А"
        },
        {
            "week_number": 2,
            "day_of_week": 2,
            "group_name": "БП1-114",
            "lesson_number": 2,
            "subgroup": 0,
            "subject": "География",
            "instructor": "Рунг К.М.",
            "classroom": "1 А"
        },
        {
            "week_number": 2,
            "day_of_week": 2,
            "group_name": "БП1-114",
            "lesson_number": 3,
            "subgroup": 0,
            "subject": "Биология",
            "instructor": "Незванова Н.М.",
            "classroom": "411"
        },
        {
            "week_number": 2,
            "day_of_week": 2,
            "group_name": "БП2-112",
            "lesson_number": 1,
            "subgroup": 0,
            "subject": "Правовое обесп. проф.деятельности",
            "instructor": "Смальцева М.Н.",
            "classroom": "426"
        },
        {
            "week_number": 2,
            "day_of_week": 2,
            "group_name": "БП2-112",
            "lesson_number": 2,
            "subgroup": 0,
            "subject": "Физ-ра",
            "instructor": "Петрушков А.В.",
            "classroom": "С.з 3к"
        },
        {
            "week_number": 2,
            "day_of_week": 2,
            "group_name": "БП2-113",
            "lesson_number": 2,
            "subgroup": 2,
            "subject": "Осн алгоритмизации",
            "instructor": "Сотников А.Е.",
            "classroom": "544"
        },
        {
            "week_number": 2,
            "day_of_week": 2,
            "group_name": "БП2-113",
            "lesson_number": 3,
            "subgroup": 1,
            "subject": "Осн.проект.БД",
            "instructor": "Нестеренко Д.М.",
            "classroom": "РЦ-1"
        },
        {
            "week_number": 2,
            "day_of_week": 2,
            "group_name": "БП2-113",
            "lesson_number": 4,
            "subgroup": 1,
            "subject": "Осн.проект.БД",
            "instructor": "Нестеренко Д.М.",
            "classroom": "РЦ-1"
        },
        {
            "week_number": 2,
            "day_of_week": 2,
            "group_name": "БП2-114",
            "lesson_number": 1,
            "subgroup": 0,
            "subject": "Рус.язык",
            "instructor": "Царегородцева Е.В.",
            "classroom": "206"
        },
        {
            "week_number": 2,
            "day_of_week": 2,
            "group_name": "БП2-114",
            "lesson_number": 4,
            "subgroup": 0,
            "subject": "Физика",
            "instructor": "Репин П.В.",
            "classroom": "124"
        },
        {
            "week_number": 2,
            "day_of_week": 2,
            "group_name": "ЭК1-203",
            "lesson_number": 2,
            "subgroup": 0,
            "subject": "Правила ТБ пром.санит.и пож.без.",
            "instructor": "Карабут М.В.",
            "classroom": "423"
        },
        {
            "week_number": 2,
            "day_of_week": 2,
            "group_name": "ЭК1-203",
            "lesson_number": 3,
            "subgroup": 0,
            "subject": "Правила ТБ пром.санит.и пож.без.",
            "instructor": "Карабут М.В.",
            "classroom": "423"
        },
        {
            "week_number": 2,
            "day_of_week": 2,
            "group_name": "ЭК1-204",
            "lesson_number": 4,
            "subgroup": 0,
            "subject": "Осн.безоп.защ.Родины",
            "instructor": "Рогова А.Ф.",
            "classroom": "Экск"
        },
        {
            "week_number": 2,
            "day_of_week": 2,
            "group_name": "ЭК2-204",
            "lesson_number": 1,
            "subgroup": 1,
            "subject": "УП.05",
            "instructor": "Годзина Е.А.",
            "classroom": "537"
        },
        {
            "week_number": 2,
            "day_of_week": 2,
            "group_name": "ЭК2-204",
            "lesson_number": 2,
            "subgroup": 1,
            "subject": "УП.05",
            "instructor": "Годзина Е.А.",
            "classroom": "537"
        },
        {
            "week_number": 2,
            "day_of_week": 2,
            "group_name": "ЭК2-204",
            "lesson_number": 2,
            "subgroup": 2,
            "subject": "Осн.пригот.проб",
            "instructor": "Вайц О.О.",
            "classroom": "РЦ-10"
        },
        {
            "week_number": 2,
            "day_of_week": 2,
            "group_name": "БМ-221",
            "lesson_number": 1,
            "subgroup": 0,
            "subject": "Орг.налад.работ по пром.оборуд.",
            "instructor": "Попов Е.П.",
            "classroom": "2"
        },
        {
            "week_number": 2,
            "day_of_week": 2,
            "group_name": "БМ-221",
            "lesson_number": 2,
            "subgroup": 0,
            "subject": "Орг.монт.работ пром.оборуд.",
            "instructor": "Попов Е.П.",
            "classroom": "2"
        },
        {
            "week_number": 2,
            "day_of_week": 2,
            "group_name": "БМ-221",
            "lesson_number": 4,
            "subgroup": 0,
            "subject": "Физ-ра",
            "instructor": "Федоренко Е.А.",
            "classroom": "ЭКСКУР"
        },
        {
            "week_number": 2,
            "day_of_week": 2,
            "group_name": "БМ-222",
            "lesson_number": 1,
            "subgroup": 0,
            "subject": "Физ-ра",
            "instructor": "Федоренко Е.А.",
            "classroom": "С.з 1к"
        },
        {
            "week_number": 2,
            "day_of_week": 2,
            "group_name": "БМ-223",
            "lesson_number": 3,
            "subgroup": 0,
            "subject": "Материаловед.",
            "instructor": "Сулейменова Д.Б.",
            "classroom": "213"
        },
        {
            "week_number": 2,
            "day_of_week": 2,
            "group_name": "БМ-224",
            "lesson_number": 3,
            "subgroup": 2,
            "subject": "Ин.яз.",
            "instructor": "Угарова А.С.",
            "classroom": "301"
        },
        {
            "week_number": 2,
            "day_of_week": 2,
            "group_name": "БМ-224",
            "lesson_number": 4,
            "subgroup": 0,
            "subject": "ФК",
            "instructor": "Первухин И.С.",
            "classroom": "с/з 1к"
        },
        {
            "week_number": 2,
            "day_of_week": 2,
            "group_name": "О-24",
            "lesson_number": 5,
            "subgroup": 0,
            "subject": "Физ-ра",
            "instructor": "Петрушков А.В.",
            "classroom": "С.з 3к"
        },
        {
            "week_number": 2,
            "day_of_week": 2,
            "group_name": "БХ1-31",
            "lesson_number": 3,
            "subgroup": 0,
            "subject": "Осн.управл.персоналом",
            "instructor": "Лагута И.С.",
            "classroom": "305"
        },
        {
            "week_number": 2,
            "day_of_week": 2,
            "group_name": "БХ1-34",
            "lesson_number": 1,
            "subgroup": 0,
            "subject": "ФК",
            "instructor": "Петрушков А.В.",
            "classroom": "С/з 3 к"
        },
        {
            "week_number": 2,
            "day_of_week": 2,
            "group_name": "БХ1-32",
            "lesson_number": 2,
            "subgroup": 0,
            "subject": "Процессы и аппараты",
            "instructor": "Гербсоммер А.В.",
            "classroom": "313"
        },
        {
            "week_number": 2,
            "day_of_week": 2,
            "group_name": "БП1-111",
            "lesson_number": 5,
            "subgroup": 1,
            "subject": "Разработ.мобил.приложений",
            "instructor": "Сотников А.Е.",
            "classroom": "544"
        },
        {
            "week_number": 2,
            "day_of_week": 2,
            "group_name": "БП1-111",
            "lesson_number": 5,
            "subgroup": 2,
            "subject": "Разработ.мобил.приложений",
            "instructor": "Польченко А.О.",
            "classroom": "547"
        },
        {
            "week_number": 2,
            "day_of_week": 2,
            "group_name": "БП1-111",
            "lesson_number": 6,
            "subgroup": 1,
            "subject": "Разработ.мобил.приложений",
            "instructor": "Сотников А.Е.",
            "classroom": "544"
        },
        {
            "week_number": 2,
            "day_of_week": 2,
            "group_name": "БП2-111",
            "lesson_number": 1,
            "subgroup": 1,
            "subject": "Разработ.мобил.приложений",
            "instructor": "Сотников А.Е.",
            "classroom": "544"
        },
        {
            "week_number": 2,
            "day_of_week": 2,
            "group_name": "БП2-111",
            "lesson_number": 1,
            "subgroup": 2,
            "subject": "Разраб.прог.модулей",
            "instructor": "Польченко А.О.",
            "classroom": "543"
        },
        {
            "week_number": 2,
            "day_of_week": 2,
            "group_name": "БП2-111",
            "lesson_number": 3,
            "subgroup": 1,
            "subject": "Инст.ср-ва разраб. ПО",
            "instructor": "Польченко А.О.",
            "classroom": "РЦ-4"
        },
        {
            "week_number": 2,
            "day_of_week": 2,
            "group_name": "БП2-111",
            "lesson_number": 4,
            "subgroup": 1,
            "subject": "Инст.ср-ва разраб. ПО",
            "instructor": "Польченко А.О.",
            "classroom": "РЦ-4"
        },
        {
            "week_number": 2,
            "day_of_week": 2,
            "group_name": "С-72",
            "lesson_number": 5,
            "subgroup": 0,
            "subject": "Осн.проект.технол.процессов",
            "instructor": "Борисова Л.В.",
            "classroom": "311"
        },
        {
            "week_number": 2,
            "day_of_week": 2,
            "group_name": "С-73",
            "lesson_number": 3,
            "subgroup": 2,
            "subject": "Информ.",
            "instructor": "Ефимова Ю.А.",
            "classroom": "543"
        },
        {
            "week_number": 2,
            "day_of_week": 2,
            "group_name": "С-73",
            "lesson_number": 6,
            "subgroup": 0,
            "subject": "Материаловед.",
            "instructor": "Борисова Л.В.",
            "classroom": "311"
        },
        {
            "week_number": 2,
            "day_of_week": 2,
            "group_name": "КИП1-193",
            "lesson_number": 4,
            "subgroup": 0,
            "subject": "Осн.тех.мех.",
            "instructor": "Смоилова С.К.",
            "classroom": "204"
        },
        {
            "week_number": 2,
            "day_of_week": 2,
            "group_name": "КИП1-194",
            "lesson_number": 1,
            "subgroup": 1,
            "subject": "Ин.яз.",
            "instructor": "Ермакова Н.В.",
            "classroom": "427"
        },
        {
            "week_number": 2,
            "day_of_week": 2,
            "group_name": "КИП1-194",
            "lesson_number": 1,
            "subgroup": 2,
            "subject": "Ин.яз.",
            "instructor": "Угарова А.С.",
            "classroom": "301"
        },
        {
            "week_number": 2,
            "day_of_week": 2,
            "group_name": "НП-161",
            "lesson_number": 4,
            "subgroup": 0,
            "subject": "Ремонт.работы",
            "instructor": "Рунг К.М.",
            "classroom": "1 А"
        },
        {
            "week_number": 2,
            "day_of_week": 2,
            "group_name": "НП-161",
            "lesson_number": 5,
            "subgroup": 0,
            "subject": "Ремонт.работы",
            "instructor": "Рунг К.М.",
            "classroom": "1 А"
        },
        {
            "week_number": 2,
            "day_of_week": 2,
            "group_name": "НП-164",
            "lesson_number": 6,
            "subgroup": 2,
            "subject": "Ин.яз.",
            "instructor": "Угарова А.С.",
            "classroom": "301"
        },
        {
            "week_number": 2,
            "day_of_week": 2,
            "group_name": "ТО-82",
            "lesson_number": 1,
            "subgroup": 0,
            "subject": "Техн.ремонт",
            "instructor": "Горобей С.С.",
            "classroom": "9"
        },
        {
            "week_number": 2,
            "day_of_week": 2,
            "group_name": "ТО-84",
            "lesson_number": 2,
            "subgroup": 0,
            "subject": "Теор.осн.теплотех.и гидравлики",
            "instructor": "Глухов С.В.",
            "classroom": "6"
        },
        {
            "week_number": 2,
            "day_of_week": 2,
            "group_name": "ТО-84",
            "lesson_number": 3,
            "subgroup": 0,
            "subject": "Теор.осн.теплотех.и гидравлики",
            "instructor": "Глухов С.В.",
            "classroom": "6"
        },
        {
            "week_number": 2,
            "day_of_week": 2,
            "group_name": "Л1-13",
            "lesson_number": 1,
            "subgroup": 2,
            "subject": "Аналитич.химия",
            "instructor": "Шарапаева А.С.",
            "classroom": "РЦ-12"
        },
        {
            "week_number": 2,
            "day_of_week": 2,
            "group_name": "Л1-13",
            "lesson_number": 2,
            "subgroup": 2,
            "subject": "Аналитич.химия",
            "instructor": "Шарапаева А.С.",
            "classroom": "РЦ-12"
        },
        {
            "week_number": 2,
            "day_of_week": 2,
            "group_name": "Л1-13",
            "lesson_number": 3,
            "subgroup": 1,
            "subject": "Аналитич.химия",
            "instructor": "Шарапаева А.С.",
            "classroom": "РЦ-12"
        },
        {
            "week_number": 2,
            "day_of_week": 2,
            "group_name": "Л-12",
            "lesson_number": 4,
            "subgroup": 2,
            "subject": "ФКХ",
            "instructor": "Шарапаева А.С.",
            "classroom": "РЦ-12"
        },
        {
            "week_number": 2,
            "day_of_week": 2,
            "group_name": "Э-41",
            "lesson_number": 1,
            "subgroup": 0,
            "subject": "УП.01",
            "instructor": "Ахметова А.С.",
            "classroom": "314"
        },
        {
            "week_number": 2,
            "day_of_week": 2,
            "group_name": "Э-41",
            "lesson_number": 2,
            "subgroup": 0,
            "subject": "УП.01",
            "instructor": "Ахметова А.С.",
            "classroom": "314"
        },
        {
            "week_number": 2,
            "day_of_week": 2,
            "group_name": "Э-42",
            "lesson_number": 1,
            "subgroup": 1,
            "subject": "Тех.рег.и контроль кач-ва",
            "instructor": "Ряписов В.П.",
            "classroom": "210"
        },
        {
            "week_number": 2,
            "day_of_week": 2,
            "group_name": "Э-42",
            "lesson_number": 1,
            "subgroup": 2,
            "subject": "Ин.яз.в ПД",
            "instructor": "Кашуба Н.Ю.",
            "classroom": "413"
        },
        {
            "week_number": 2,
            "day_of_week": 2,
            "group_name": "Э-42",
            "lesson_number": 2,
            "subgroup": 2,
            "subject": "Ин.яз.в ПД",
            "instructor": "Кашуба Н.Ю.",
            "classroom": "413"
        },
        {
            "week_number": 2,
            "day_of_week": 2,
            "group_name": "Э-42",
            "lesson_number": 4,
            "subgroup": 2,
            "subject": "Тех.рег.и контроль кач-ва",
            "instructor": "Ряписов В.П.",
            "classroom": "210"
        },
        {
            "week_number": 2,
            "day_of_week": 2,
            "group_name": "Э-43",
            "lesson_number": 5,
            "subgroup": 0,
            "subject": "Матем.",
            "instructor": "Бакаева С.Х.",
            "classroom": "226"
        },
        {
            "week_number": 2,
            "day_of_week": 2,
            "group_name": "ХТ-251",
            "lesson_number": 5,
            "subgroup": 2,
            "subject": "ВР по проф. Оператор тех.установки",
            "instructor": "Годзина Е.А.",
            "classroom": "537"
        },
        {
            "week_number": 2,
            "day_of_week": 2,
            "group_name": "ХТ-252",
            "lesson_number": 1,
            "subgroup": 0,
            "subject": "Процессы  и аппараты",
            "instructor": "Первухина Т.В.",
            "classroom": "316"
        },
        {
            "week_number": 2,
            "day_of_week": 2,
            "group_name": "ХТ-252",
            "lesson_number": 2,
            "subgroup": 0,
            "subject": "Физ-ра",
            "instructor": "Первухин И.С.",
            "classroom": "с/з 1к"
        },
        {
            "week_number": 2,
            "day_of_week": 2,
            "group_name": "ХТ-252",
            "lesson_number": 4,
            "subgroup": 1,
            "subject": "Ин.яз.",
            "instructor": "Ермакова Н.В.",
            "classroom": "427"
        },
        {
            "week_number": 2,
            "day_of_week": 2,
            "group_name": "ХТ-254",
            "lesson_number": 3,
            "subgroup": 0,
            "subject": "Осн.безоп.защ.Родины",
            "instructor": "Первухин И.С.",
            "classroom": "23а"
        },
        {
            "week_number": 2,
            "day_of_week": 2,
            "group_name": "ББ-122",
            "lesson_number": 1,
            "subgroup": 0,
            "subject": "Аудит",
            "instructor": "Ольшевская Г.Ц.",
            "classroom": "533"
        },
        {
            "week_number": 2,
            "day_of_week": 2,
            "group_name": "ББ-122",
            "lesson_number": 2,
            "subgroup": 0,
            "subject": "Аудит",
            "instructor": "Ольшевская Г.Ц.",
            "classroom": "533"
        },
        {
            "week_number": 2,
            "day_of_week": 2,
            "group_name": "ББ-123",
            "lesson_number": 2,
            "subgroup": 1,
            "subject": "Информ.тех-гии в ПД",
            "instructor": "Старикова А.С.",
            "classroom": "542"
        },
        {
            "week_number": 2,
            "day_of_week": 2,
            "group_name": "ББ-123",
            "lesson_number": 3,
            "subgroup": 2,
            "subject": "Информ.тех-гии в ПД",
            "instructor": "Старикова А.С.",
            "classroom": "542"
        },
        {
            "week_number": 2,
            "day_of_week": 2,
            "group_name": "ББ-123",
            "lesson_number": 4,
            "subgroup": 2,
            "subject": "Информ.тех-гии в ПД",
            "instructor": "Старикова А.С.",
            "classroom": "542"
        },
        {
            "week_number": 2,
            "day_of_week": 2,
            "group_name": "ЭС-172",
            "lesson_number": 4,
            "subgroup": 0,
            "subject": "Физ-ра",
            "instructor": "Мальцева Т.А.",
            "classroom": "С/з 3 к"
        },
        {
            "week_number": 2,
            "day_of_week": 2,
            "group_name": "ЭС-173",
            "lesson_number": 2,
            "subgroup": 2,
            "subject": "Информ.тех-гии в ПД",
            "instructor": "Вальян В.Г.",
            "classroom": "РЦ-1"
        },
        {
            "week_number": 2,
            "day_of_week": 2,
            "group_name": "ЭС-173",
            "lesson_number": 4,
            "subgroup": 0,
            "subject": "Тех.экспл.ЭЭС",
            "instructor": "Горобей С.С.",
            "classroom": "9"
        },
        {
            "week_number": 2,
            "day_of_week": 2,
            "group_name": "ЭС-174",
            "lesson_number": 3,
            "subgroup": 0,
            "subject": "Физ-ра",
            "instructor": "Мальцева Т.А.",
            "classroom": "С/з 3"
        },
        {
            "week_number": 2,
            "day_of_week": 2,
            "group_name": "ЭМ1-103",
            "lesson_number": 1,
            "subgroup": 1,
            "subject": "УП.01",
            "instructor": "Конев Е.В.",
            "classroom": "7"
        },
        {
            "week_number": 2,
            "day_of_week": 2,
            "group_name": "ЭМ1-103",
            "lesson_number": 1,
            "subgroup": 2,
            "subject": "УП.01",
            "instructor": "Белова Н.А.",
            "classroom": "РЦ-6"
        },
        {
            "week_number": 2,
            "day_of_week": 2,
            "group_name": "ЭМ1-103",
            "lesson_number": 2,
            "subgroup": 1,
            "subject": "УП.01",
            "instructor": "Конев Е.В.",
            "classroom": "7"
        },
        {
            "week_number": 2,
            "day_of_week": 2,
            "group_name": "ЭМ1-103",
            "lesson_number": 2,
            "subgroup": 2,
            "subject": "УП.01",
            "instructor": "Белова Н.А.",
            "classroom": "РЦ-6"
        },
        {
            "week_number": 2,
            "day_of_week": 2,
            "group_name": "ЭМ1-103",
            "lesson_number": 3,
            "subgroup": 1,
            "subject": "УП.01",
            "instructor": "Конев Е.В.",
            "classroom": "7"
        },
        {
            "week_number": 2,
            "day_of_week": 2,
            "group_name": "ЭМ1-103",
            "lesson_number": 3,
            "subgroup": 2,
            "subject": "УП.01",
            "instructor": "Белова Н.А.",
            "classroom": "РЦ-6"
        },
        {
            "week_number": 2,
            "day_of_week": 2,
            "group_name": "ЭМ1-103",
            "lesson_number": 4,
            "subgroup": 0,
            "subject": "КИП (МДК.02.02)",
            "instructor": "Карабут М.В.",
            "classroom": "426"
        },
        {
            "week_number": 2,
            "day_of_week": 2,
            "group_name": "ЭМ1-104",
            "lesson_number": 4,
            "subgroup": 0,
            "subject": "Биология",
            "instructor": "Незванова Н.М.",
            "classroom": "411"
        },
        {
            "week_number": 2,
            "day_of_week": 2,
            "group_name": "ЭМ2-103",
            "lesson_number": 4,
            "subgroup": 0,
            "subject": "Орг.и техн-гия проверки эл/оборуд.",
            "instructor": "Белова Н.А.",
            "classroom": "РЦ-5"
        },
        {
            "week_number": 2,
            "day_of_week": 2,
            "group_name": "ЭМ2-104",
            "lesson_number": 1,
            "subgroup": 0,
            "subject": "Физ-ра",
            "instructor": "Первухин И.С.",
            "classroom": "с/з 1к"
        },
        {
            "week_number": 2,
            "day_of_week": 2,
            "group_name": "ЭМ2-104",
            "lesson_number": 3,
            "subgroup": 0,
            "subject": "География",
            "instructor": "Рунг К.М.",
            "classroom": "1 А"
        },
        {
            "week_number": 2,
            "day_of_week": 2,
            "group_name": "ЭТ-132",
            "lesson_number": 3,
            "subgroup": 1,
            "subject": "Ин.яз.в ПД",
            "instructor": "Кашуба Н.Ю.",
            "classroom": "413"
        },
        {
            "week_number": 2,
            "day_of_week": 2,
            "group_name": "ЭТ-132",
            "lesson_number": 4,
            "subgroup": 1,
            "subject": "Ин.яз.в ПД",
            "instructor": "Кашуба Н.Ю.",
            "classroom": "413"
        },
        {
            "week_number": 2,
            "day_of_week": 2,
            "group_name": "БЮ-154",
            "lesson_number": 2,
            "subgroup": 0,
            "subject": "БЖД",
            "instructor": "Рогова А.Ф.",
            "classroom": "Чит.з"
        }
    ]
}